Metadata-Version: 2.1
Name: simple-form
Version: 1.3
Summary: Pequena biblioteca para facilitar formulários em CLI com Python
Home-page: https://github.com/Hoyasumii/SimpleForm
Author: Alan Reis Anjos
Author-email: alanreisanjo@gmail.com
License: GPL-3.0
License-File: LICENSE
Requires-Dist: keyboard==0.13.5
Requires-Dist: setuptools==69.0.3
